common/__init__.py
common/descriptors.py
common/variables.py
database/__init__.py
database/client_database.py
deсorators/__init__.py
deсorators/call_logger.py
deсorators/login_required.py
gui/__init__.py
gui/add_contact.py
gui/del_contact.py
gui/main_window.py
gui/main_window_conv.py
gui/start_dialog.py
loggers/__init__.py
loggers/client_logs.py
messagers/__init__.py
messagers/abstract_messenger.py
messagers/client_messenger.py
meta_classes/__init__.py
meta_classes/client_maker.py
async_message_client-0.0.1.dist-info/METADATA
async_message_client-0.0.1.dist-info/WHEEL
async_message_client-0.0.1.dist-info/top_level.txt
async_message_client-0.0.1.dist-info/RECORD
